pygtop/__init__.py
pygtop/exceptions.py
pygtop/gtop.py
pygtop/interactions.py
pygtop/ligands.py
pygtop/pdb.py
pygtop/shared.py
pygtop/targets.py
pygtop-2.1.4.dist-info/DESCRIPTION.rst
pygtop-2.1.4.dist-info/METADATA
pygtop-2.1.4.dist-info/RECORD
pygtop-2.1.4.dist-info/WHEEL
pygtop-2.1.4.dist-info/metadata.json
pygtop-2.1.4.dist-info/top_level.txt
