Metadata-Version: 2.0
Name: pygtop
Version: 2.1.4
Summary: A Python wrapper for the Guide to PHARMACOLOGY API. It provides  a Python interface for access to the GtoP database.
Home-page: https://pygtop.readthedocs.org
Author: Sam Ireland
Author-email: Sam.Ireland@ed.ac.uk
License: MIT
Keywords: pharmacology drugs chemistry bioinformatics
Platform: UNKNOWN
Classifier: Development Status :: 4 - Beta
Classifier: Intended Audience :: Science/Research
Classifier: License :: OSI Approved :: MIT License
Classifier: Topic :: Scientific/Engineering :: Chemistry
Classifier: Programming Language :: Python :: 3
Classifier: Programming Language :: Python :: 3.0
Classifier: Programming Language :: Python :: 3.1
Classifier: Programming Language :: Python :: 3.2
Classifier: Programming Language :: Python :: 3.3
Classifier: Programming Language :: Python :: 3.4
Classifier: Programming Language :: Python :: 3.5
Classifier: Programming Language :: Python :: 3.6
Classifier: Programming Language :: Python :: 3.7
Requires-Dist: molecupy
Requires-Dist: requests
